starlette_fancy/__init__.py
starlette_fancy/utils.py
starlette_fancy/endpoints/__init__.py
starlette_fancy/endpoints/crud.py
starlette_fancy/mixins/__init__.py
starlette_fancy/mixins/crud.py
starlette_fancy/processors/__init__.py
starlette_fancy/processors/databases.py
starlette_fancy/validators/__init__.py
starlette_fancy/validators/pydantic.py
starlette_fancy-0.1.0.dist-info/LICENSE
starlette_fancy-0.1.0.dist-info/METADATA
starlette_fancy-0.1.0.dist-info/WHEEL
starlette_fancy-0.1.0.dist-info/top_level.txt
starlette_fancy-0.1.0.dist-info/RECORD
