Metadata-Version: 2.1
Name: starlette-fancy
Version: 0.1.0
Summary: Fancy toolkit for Starlette
Home-page: https://github.com/xtarlette/starlette-fancy
Author: Xurvan
Author-email: xojtaba@gmail.com
License: Apache License 2.0
Project-URL: Source, https://github.com/xtarlette/starlette-fancy
Project-URL: Tracker, https://github.com/xtarlette/starlette-fancy/issues
Platform: UNKNOWN
Classifier: Development Status :: 3 - Alpha
Classifier: Intended Audience :: Developers
Classifier: Topic :: Software Development
Classifier: License :: OSI Approved :: Apache Software License
Classifier: Programming Language :: Python :: 3
Requires-Python: >=3.8
License-File: LICENSE
Requires-Dist: starlette (>=0.17)
Provides-Extra: databases
Requires-Dist: databases ; extra == 'databases'
Provides-Extra: full
Requires-Dist: pydantic ; extra == 'full'
Requires-Dist: databases ; extra == 'full'
Requires-Dist: starlette-marshal ; extra == 'full'
Requires-Dist: python-rapidjson ; extra == 'full'
Provides-Extra: marshal
Requires-Dist: starlette-marshal ; extra == 'marshal'
Provides-Extra: pydantic
Requires-Dist: pydantic ; extra == 'pydantic'
